{
  "weather": {
    "c": 12,
    "f": 54,
    "kmh": 11,
    "mph": 7,
    "winddir": 170,
    "icon": "rain",
    "_ts": "2026-03-05T15:51:07.021Z"
  },
  "tides2d": {
    "_date": "2026-03-05",
    "todayKey": "2026-03-05",
    "tomorrowKey": "2026-03-06",
    "todayItems": [
      "↓ Low 00:30 — -3.7 m",
      "↑ High 06:32 — 3.7 m",
      "↓ Low 12:50 — -3.7 m",
      "↑ High 18:49 — 3.4 m"
    ],
    "tomorrowItems": [
      "↓ Low 01:01 — -3.6 m",
      "↑ High 07:05 — 3.5 m",
      "↓ Low 13:19 — -3.5 m",
      "↑ High 19:20 — 3.2 m"
    ]
  },
  "astronomy": {
    "sunrise": "06:29 AM",
    "sunset": "05:52 PM",
    "phaseName": "Waning Gibbous",
    "phaseIcon": "waning-gibbous",
    "_date": "2026-03-05"
  }
}